{
  "info": {
    "name": "Gold Price API",
    "description": "API endpoints for fetching live gold prices (XAU/USD)",
    "schema": "https://schema.getpostman.com/json/collection/v2.1.0/collection.json"
  },
  "item": [
    {
      "name": "Get Gold Price",
      "request": {
        "method": "GET",
        "header": [],
        "url": {
          "raw": "{{BASE_URL}}/api/gold",
          "host": ["{{BASE_URL}}"],
          "path": ["api", "gold"]
        },
        "description": "Get live gold price (XAU/USD) without caching.\n\nReturns:\n- price: Current gold price\n- currency: USD\n- lastUpdate: Timestamp of last update\n- description: Information about gold (from database)\n- coverImage: Gold trading image URL (from database)"
      },
      "response": [
        {
          "name": "Success Response",
          "originalRequest": {
            "method": "GET",
            "header": [],
            "url": {
              "raw": "{{BASE_URL}}/api/gold",
              "host": ["{{BASE_URL}}"],
              "path": ["api", "gold"]
            }
          },
          "status": "OK",
          "code": 200,
          "_postman_previewlanguage": "json",
          "header": [
            {
              "key": "Content-Type",
              "value": "application/json"
            }
          ],
          "body": "{\n  \"success\": true,\n  \"data\": {\n    \"price\": \"2034.56\",\n    \"currency\": \"USD\",\n    \"lastUpdate\": \"2026-02-11T10:30:00.000Z\",\n    \"description\": \"Gold is one of the most traded precious metals in the world. It is widely used as a safe haven asset and its price changes based on global markets and demand.\",\n    \"coverImage\": \"https://images.unsplash.com/photo-1610375461246-83df859d849d?w=800&q=80\"\n  },\n  \"timestamp\": \"2026-02-11T10:30:15.123Z\"\n}"
        },
        {
          "name": "API Unavailable",
          "originalRequest": {
            "method": "GET",
            "header": [],
            "url": {
              "raw": "{{BASE_URL}}/api/gold",
              "host": ["{{BASE_URL}}"],
              "path": ["api", "gold"]
            }
          },
          "status": "Service Unavailable",
          "code": 503,
          "_postman_previewlanguage": "json",
          "header": [
            {
              "key": "Content-Type",
              "value": "application/json"
            }
          ],
          "body": "{\n  \"success\": false,\n  \"error\": \"Gold price API is currently unavailable\"\n}"
        }
      ]
    },
    {
      "name": "Get Gold Price (Cached)",
      "request": {
        "method": "GET",
        "header": [],
        "url": {
          "raw": "{{BASE_URL}}/api/gold/cached",
          "host": ["{{BASE_URL}}"],
          "path": ["api", "gold", "cached"]
        },
        "description": "Get live gold price with caching for better performance.\n\nCache Duration: 30 seconds\n\nReturns:\n- price: Current gold price\n- currency: USD\n- lastUpdate: Timestamp of last update\n- description: Information about gold\n- coverImage: Gold trading image URL\n- cached: Whether data is from cache\n- cacheAge: Age of cache in seconds (if cached)"
      },
      "response": [
        {
          "name": "Success Response (Fresh)",
          "originalRequest": {
            "method": "GET",
            "header": [],
            "url": {
              "raw": "{{BASE_URL}}/api/gold/cached",
              "host": ["{{BASE_URL}}"],
              "path": ["api", "gold", "cached"]
            }
          },
          "status": "OK",
          "code": 200,
          "_postman_previewlanguage": "json",
          "header": [
            {
              "key": "Content-Type",
              "value": "application/json"
            }
          ],
          "body": "{\n  \"success\": true,\n  \"data\": {\n    \"price\": \"2034.56\",\n    \"currency\": \"USD\",\n    \"lastUpdate\": \"2026-02-11T10:30:00.000Z\",\n    \"description\": \"Gold is one of the most traded precious metals in the world. It is widely used as a safe haven asset and its price changes based on global markets and demand.\",\n    \"coverImage\": \"https://images.unsplash.com/photo-1610375461246-83df859d849d?w=800&q=80\"\n  },\n  \"timestamp\": \"2026-02-11T10:30:15.123Z\",\n  \"cached\": false\n}"
        },
        {
          "name": "Success Response (Cached)",
          "originalRequest": {
            "method": "GET",
            "header": [],
            "url": {
              "raw": "{{BASE_URL}}/api/gold/cached",
              "host": ["{{BASE_URL}}"],
              "path": ["api", "gold", "cached"]
            }
          },
          "status": "OK",
          "code": 200,
          "_postman_previewlanguage": "json",
          "header": [
            {
              "key": "Content-Type",
              "value": "application/json"
            }
          ],
          "body": "{\n  \"success\": true,\n  \"data\": {\n    \"price\": \"2034.56\",\n    \"currency\": \"USD\",\n    \"lastUpdate\": \"2026-02-11T10:30:00.000Z\",\n    \"description\": \"Gold is one of the most traded precious metals in the world. It is widely used as a safe haven asset and its price changes based on global markets and demand.\",\n    \"coverImage\": \"https://images.unsplash.com/photo-1610375461246-83df859d849d?w=800&q=80\"\n  },\n  \"timestamp\": \"2026-02-11T10:30:15.123Z\",\n  \"cached\": true,\n  \"cacheAge\": 15\n}"
        },
        {
          "name": "Stale Cache (API Error)",
          "originalRequest": {
            "method": "GET",
            "header": [],
            "url": {
              "raw": "{{BASE_URL}}/api/gold/cached",
              "host": ["{{BASE_URL}}"],
              "path": ["api", "gold", "cached"]
            }
          },
          "status": "OK",
          "code": 200,
          "_postman_previewlanguage": "json",
          "header": [
            {
              "key": "Content-Type",
              "value": "application/json"
            }
          ],
          "body": "{\n  \"success\": true,\n  \"data\": {\n    \"price\": \"2034.56\",\n    \"currency\": \"USD\",\n    \"lastUpdate\": \"2026-02-11T10:30:00.000Z\",\n    \"description\": \"Gold is one of the most traded precious metals in the world. It is widely used as a safe haven asset and its price changes based on global markets and demand.\",\n    \"coverImage\": \"https://images.unsplash.com/photo-1610375461246-83df859d849d?w=800&q=80\"\n  },\n  \"timestamp\": \"2026-02-11T10:30:15.123Z\",\n  \"cached\": true,\n  \"stale\": true,\n  \"warning\": \"Returning cached data due to API error\"\n}"
        }
      ]
    },
    {
      "name": "Get Gold Config",
      "request": {
        "method": "GET",
        "header": [],
        "url": {
          "raw": "{{BASE_URL}}/api/gold/config",
          "host": ["{{BASE_URL}}"],
          "path": ["api", "gold", "config"]
        },
        "description": "Get gold configuration (description & coverImage).\n\nPublic endpoint - no authentication required."
      },
      "response": [
        {
          "name": "Success Response",
          "originalRequest": {
            "method": "GET",
            "header": [],
            "url": {
              "raw": "{{BASE_URL}}/api/gold/config",
              "host": ["{{BASE_URL}}"],
              "path": ["api", "gold", "config"]
            }
          },
          "status": "OK",
          "code": 200,
          "_postman_previewlanguage": "json",
          "header": [
            {
              "key": "Content-Type",
              "value": "application/json"
            }
          ],
          "body": "{\n  \"success\": true,\n  \"data\": {\n    \"description\": \"Gold is one of the most traded precious metals in the world. It is widely used as a safe haven asset and its price changes based on global markets and demand.\",\n    \"coverImage\": \"https://images.unsplash.com/photo-1610375461246-83df859d849d?w=800&q=80\",\n    \"isActive\": true,\n    \"updatedAt\": \"2026-02-11T10:30:00.000Z\"\n  }\n}"
        }
      ]
    },
    {
      "name": "Create Gold Config",
      "request": {
        "method": "POST",
        "header": [
          {
            "key": "Authorization",
            "value": "Bearer {{ADMIN_TOKEN}}",
            "type": "text"
          },
          {
            "key": "Content-Type",
            "value": "application/json",
            "type": "text"
          }
        ],
        "body": {
          "mode": "raw",
          "raw": "{\n  \"description\": \"Gold is one of the most traded precious metals in the world. It is widely used as a safe haven asset and its price changes based on global markets and demand.\",\n  \"coverImage\": \"https://images.unsplash.com/photo-1610375461246-83df859d849d?w=800&q=80\"\n}"
        },
        "url": {
          "raw": "{{BASE_URL}}/api/gold/config",
          "host": ["{{BASE_URL}}"],
          "path": ["api", "gold", "config"]
        },
        "description": "Create/Reset gold configuration.\n\nAdmin only - requires authentication.\n\nBody:\n- description (required): Gold description text\n- coverImage (required): Gold cover image URL"
      },
      "response": [
        {
          "name": "Success Response",
          "originalRequest": {
            "method": "POST",
            "header": [
              {
                "key": "Authorization",
                "value": "Bearer {{ADMIN_TOKEN}}",
                "type": "text"
              },
              {
                "key": "Content-Type",
                "value": "application/json",
                "type": "text"
              }
            ],
            "body": {
              "mode": "raw",
              "raw": "{\n  \"description\": \"Gold is one of the most traded precious metals in the world.\",\n  \"coverImage\": \"https://example.com/gold.jpg\"\n}"
            },
            "url": {
              "raw": "{{BASE_URL}}/api/gold/config",
              "host": ["{{BASE_URL}}"],
              "path": ["api", "gold", "config"]
            }
          },
          "status": "Created",
          "code": 201,
          "_postman_previewlanguage": "json",
          "header": [
            {
              "key": "Content-Type",
              "value": "application/json"
            }
          ],
          "body": "{\n  \"success\": true,\n  \"message\": \"Gold configuration created successfully\",\n  \"data\": {\n    \"description\": \"Gold is one of the most traded precious metals in the world.\",\n    \"coverImage\": \"https://example.com/gold.jpg\",\n    \"createdAt\": \"2026-02-11T10:30:00.000Z\"\n  }\n}"
        }
      ]
    },
    {
      "name": "Update Gold Config",
      "request": {
        "method": "PUT",
        "header": [
          {
            "key": "Authorization",
            "value": "Bearer {{ADMIN_TOKEN}}",
            "type": "text"
          },
          {
            "key": "Content-Type",
            "value": "application/json",
            "type": "text"
          }
        ],
        "body": {
          "mode": "raw",
          "raw": "{\n  \"description\": \"Updated gold description\",\n  \"coverImage\": \"https://new-image-url.com/gold.jpg\"\n}"
        },
        "url": {
          "raw": "{{BASE_URL}}/api/gold/config",
          "host": ["{{BASE_URL}}"],
          "path": ["api", "gold", "config"]
        },
        "description": "Update gold configuration.\n\nAdmin only - requires authentication.\n\nBody (at least one required):\n- description (optional): New gold description\n- coverImage (optional): New cover image URL"
      },
      "response": [
        {
          "name": "Success Response",
          "originalRequest": {
            "method": "PUT",
            "header": [
              {
                "key": "Authorization",
                "value": "Bearer {{ADMIN_TOKEN}}",
                "type": "text"
              },
              {
                "key": "Content-Type",
                "value": "application/json",
                "type": "text"
              }
            ],
            "body": {
              "mode": "raw",
              "raw": "{\n  \"description\": \"Updated description\"\n}"
            },
            "url": {
              "raw": "{{BASE_URL}}/api/gold/config",
              "host": ["{{BASE_URL}}"],
              "path": ["api", "gold", "config"]
            }
          },
          "status": "OK",
          "code": 200,
          "_postman_previewlanguage": "json",
          "header": [
            {
              "key": "Content-Type",
              "value": "application/json"
            }
          ],
          "body": "{\n  \"success\": true,\n  \"message\": \"Gold configuration updated successfully\",\n  \"data\": {\n    \"description\": \"Updated description\",\n    \"coverImage\": \"https://images.unsplash.com/photo-1610375461246-83df859d849d?w=800&q=80\",\n    \"updatedAt\": \"2026-02-11T10:35:00.000Z\"\n  }\n}"
        }
      ]
    }
  ],
  "variable": [
    {
      "key": "BASE_URL",
      "value": "http://localhost:3000",
      "type": "string"
    },
    {
      "key": "ADMIN_TOKEN",
      "value": "your_admin_token_here",
      "type": "string"
    }
  ]
}
